pytest_flake_detection/__init__.py
pytest_flake_detection/plugin.py
pytest_flake_detection-0.1.2.dist-info/LICENSE
pytest_flake_detection-0.1.2.dist-info/METADATA
pytest_flake_detection-0.1.2.dist-info/WHEEL
pytest_flake_detection-0.1.2.dist-info/entry_points.txt
pytest_flake_detection-0.1.2.dist-info/top_level.txt
pytest_flake_detection-0.1.2.dist-info/RECORD
