Metadata-Version: 2.1
Name: pytest-flake-detection
Version: 0.1.2
Summary: Continuously runs your tests to detect flaky tests
Author-email: Charles Turner <charles.turner@anu.edu.au>
Maintainer-email: Charles Turner <charles.turner@anu.edu.au>
License: 
Project-URL: Repository, https://github.com/charles-turner-1/pytest-flake-detection
Classifier: Framework :: Pytest
Classifier: Development Status :: 4 - Beta
Classifier: Intended Audience :: Developers
Classifier: Topic :: Software Development :: Testing
Classifier: Operating System :: OS Independent
Classifier: Programming Language :: Python
Classifier: Programming Language :: Python :: 3.8
Classifier: Programming Language :: Python :: 3.9
Classifier: Programming Language :: Python :: 3.10
Classifier: Programming Language :: Python :: 3.11
Classifier: Programming Language :: Python :: 3.12
Classifier: Programming Language :: Python :: 3 :: Only
Classifier: Programming Language :: Python :: Implementation :: CPython
Classifier: Programming Language :: Python :: Implementation :: PyPy
Classifier: License :: OSI Approved :: Apache Software License
Requires-Python: >=3.8
License-File: LICENSE
Requires-Dist: pytest>=6.2.0
